LICENSE.txt
MANIFEST.in
README.md
setup.cfg
setup.py
moveFile/__init__.py
moveFile/find_file_return_path_m1.pyd
moveFile/moveFile.pyd
moveFile/moveFileUi.pyd
moveFile/optionDb.pyd
moveFile.egg-info/PKG-INFO
moveFile.egg-info/SOURCES.txt
moveFile.egg-info/dependency_links.txt
moveFile.egg-info/top_level.txt
moveFile/Ui/__init__.py
moveFile/Ui/moveFileUi.pyd